CHANGES.txt
DESCRIPTION.rst
LICENSE
MANIFEST.in
README.md
README.rst
run_tests.py
setup.cfg
setup.py
django_quickadmin.egg-info/PKG-INFO
django_quickadmin.egg-info/SOURCES.txt
django_quickadmin.egg-info/dependency_links.txt
django_quickadmin.egg-info/requires.txt
django_quickadmin.egg-info/top_level.txt
quickadmin/__init__.py
quickadmin/apps.py
quickadmin/config.py
quickadmin/register.py
quickadmin/tests.py
quickadmin/urls.py