Metadata-Version: 1.1
Name: django-quickadmin
Version: 0.1.2
Summary: Django application automatically registers all found models into admin area
Home-page: https://github.com/zniper/django-quickadmin
Author: Ha Pham
Author-email: me.zniper@gmail.com
License: MIT
Keywords: django admin models register python
Platform: UNKNOWN
Classifier: Programming Language :: Python :: 2.6
Classifier: Programming Language :: Python :: 2.7
Classifier: Programming Language :: Python :: 3
Classifier: Programming Language :: Python :: 3.2
Classifier: Programming Language :: Python :: 3.3
Classifier: Programming Language :: Python :: 3.4
